cppgen/__init__.py
cppgen/convention.py
cppgen/cppgen.py
cppgen/hppgen.py
cppgen/nodes.py
cppgen/utils.py
cppgen-2021.3.1.dist-info/COPYING
cppgen-2021.3.1.dist-info/METADATA
cppgen-2021.3.1.dist-info/WHEEL
cppgen-2021.3.1.dist-info/entry_points.txt
cppgen-2021.3.1.dist-info/top_level.txt
cppgen-2021.3.1.dist-info/RECORD
