Metadata-Version: 2.1
Name: cppgen
Version: 2021.3.1
Summary: C/C++ definition generator
Home-page: https://github.com/kosmospredanie/cppgen
Author: Космическое П.
Author-email: kosmospredanie@yandex.ru
License: MIT
Project-URL: Source, https://github.com/kosmospredanie/cppgen
Project-URL: Bug Tracker, https://github.com/kosmospredanie/cppgen/issues
Platform: UNKNOWN
Classifier: Programming Language :: Python :: 3
Classifier: Programming Language :: Python :: 3.7
Classifier: Programming Language :: Python :: 3.8
Classifier: Programming Language :: Python :: 3.9
Classifier: License :: OSI Approved :: MIT License
Classifier: Operating System :: OS Independent
Requires-Python: >=3.7
